image_processing/__init__.py
image_processing/processing/__init__.py
image_processing/processing/combinacao.py
image_processing/processing/transformacao.py
image_processing/utils/__init__.py
image_processing/utils/io.py
image_processing/utils/plot.py
processamento_de_imagem_leonardo-0.0.2.dist-info/METADATA
processamento_de_imagem_leonardo-0.0.2.dist-info/WHEEL
processamento_de_imagem_leonardo-0.0.2.dist-info/top_level.txt
processamento_de_imagem_leonardo-0.0.2.dist-info/RECORD
