Metadata-Version: 2.4
Name: Processamento_de_imagem_leonardo
Version: 0.0.2
Summary: Image processing package using skimage
Home-page: https://github.com/Leonardojnss/Pacote-de-Python.git
Author: Leonardo_José
Requires-Python: >=3.8
Requires-Dist: matplotlib
Requires-Dist: numpy
Requires-Dist: scikit-image>=0.16.1
Dynamic: author
Dynamic: description
Dynamic: description-content-type
Dynamic: home-page
Dynamic: requires-dist
Dynamic: requires-python
Dynamic: summary
